[
  {
    "name": "Seattle",
    "local_names": {
      "oc": "Seattle",
      "eo": "Seatlo",
      "bg": "Сиатъл",
      "tt": "Сиэтл",
      "ar": "سياتيل، واشنطن",
      "lv": "Sietla",
      "uk": "Сієтл",
      "am": "ስያትል",
      "kn": "ಸಿಯಾಟಲ್",
      "ru": "Сиэтл",
      "ug": "Séatl",
      "fr": "Seattle",
      "zh": "西雅圖",
      "af": "Seattle",
      "uz": "Sietl",
      "bs": "Seattle",
      "en": "Seattle",
      "be": "Сіэтл",
      "la": "Seattlum",
      "ja": "シアトル",
      "ko": "시애틀",
      "lt": "Sietlas"
    },
    "lat": 47.6038321,
    "lon": -122.330062,
    "country": "US",
    "state": "Washington"
  }
]
